CHANGELOG.txt
Licence.txt
MANIFEST.in
readme.md
setup.py
ttkvideos/__init__.py
ttkvideos.egg-info/PKG-INFO
ttkvideos.egg-info/SOURCES.txt
ttkvideos.egg-info/dependency_links.txt
ttkvideos.egg-info/requires.txt
ttkvideos.egg-info/top_level.txt